GarNet/__init__.py
GarNet/__main__.py
GarNet/construct_garnet_file.py
GarNet/garnet.py
GarNet/summary.jinja
GarNet-0.5.0.dist-info/DESCRIPTION.rst
GarNet-0.5.0.dist-info/METADATA
GarNet-0.5.0.dist-info/RECORD
GarNet-0.5.0.dist-info/WHEEL
GarNet-0.5.0.dist-info/metadata.json
GarNet-0.5.0.dist-info/top_level.txt
