Metadata-Version: 2.0
Name: GarNet
Version: 0.5.0
Summary: UNKNOWN
Home-page: https://github.com/fraenkel-lab/GarNet
Author: zfrenchee, iamjli
Author-email: alex@lenail.org, iamjli@mit.edu
License: MIT
Platform: UNKNOWN
Classifier: Programming Language :: Python :: 3.5
Classifier: Programming Language :: Python :: 3.6
Requires-Dist: jinja2
Requires-Dist: matplotlib
Requires-Dist: numpy
Requires-Dist: pandas
Requires-Dist: pybedtools
Requires-Dist: statsmodels
